flask_session_captcha/__init__.py
flask_session_captcha-1.5.0.dist-info/LICENSE
flask_session_captcha-1.5.0.dist-info/METADATA
flask_session_captcha-1.5.0.dist-info/WHEEL
flask_session_captcha-1.5.0.dist-info/top_level.txt
flask_session_captcha-1.5.0.dist-info/RECORD
