Metadata-Version: 2.1
Name: flask_session_captcha
Version: 1.5.0
Summary: Captcha implementation for flask and flask-session.
Home-page: https://github.com/Tethik/flask-session-captcha
Author: Joakim Uddholm
Author-email: tethik@gmail.com
License: MIT
Classifier: Development Status :: 4 - Beta
Classifier: Environment :: Web Environment
Classifier: Intended Audience :: Developers
Classifier: License :: OSI Approved :: MIT License
Classifier: Operating System :: OS Independent
Classifier: Programming Language :: Python
Classifier: Topic :: Internet :: WWW/HTTP :: Dynamic Content
Classifier: Topic :: Software Development :: Libraries :: Python Modules
Classifier: Programming Language :: Python :: 3.8
Classifier: Programming Language :: Python :: 3.9
Classifier: Programming Language :: Python :: 3.10
Classifier: Programming Language :: Python :: 3.11
Classifier: Topic :: Security
License-File: LICENSE
Requires-Dist: captcha
Requires-Dist: Flask
Requires-Dist: markupsafe
